Workbook

Sheet README
A1: Local Website Business — Financial Model
B4: How to use this workbook
B5: This model turns your client count and pricing into a monthly income projection, and shows exactly
B6: how many clients you need to hit $5,000/month. Edit only the YELLOW cells — everything else
B7: calculates automatically.
B9: Tabs in this workbook:
B10: 1. Assumptions — your prices, costs, and conversion rates. Start here.
B11: 2. Monthly Projection — a 12-month build-out of clients, revenue, costs, and profit.
B12: 3. Path to $5K — shows the mix of one-time builds + recurring care plans needed to hit goal.
B13: 4. Lead Tracker — a simple CRM for logging prospects found via Google Maps/Yelp, with status.
B15: Key idea: one-time website builds give you cash bursts, but MONTHLY CARE PLAN clients are what
B16: make $5,000/month stable. The Path to $5K tab shows why a mix of both is more realistic than
B17: relying on new sales every single month.
... B20: adjust the yellow cells in Assumptions to match your real numbers as you learn them.

Sheet Assumptions
A1: Assumptions (edit yellow cells)
B3: Pricing
B4: Item | C4: Value | E4: Calculated: new clients won per month | F4: =ROUND(C19*4*C20*C21,1) -> 2.4
B5: One-time build fee (per new client) | C5: 1200 | E5: Calculated: weekly conversations | F5: =ROUND(C19*C20,1) -> 5
B6: Deposit % collected upfront | C6: 0.5 | E6: These funnel rates are rough starting estimates — track real numbers in the Lead Tracker tab and update the yellow cells above as you learn your actual conversion rates.
B7: Monthly care plan fee (per client) | C7: 99
B8: Domain cost passed to client (per year) | C8: 15
B10: Your Costs (per client)
B11: Item | C11: Value
B12: Hosting cost per site (per month) | C12: 3
B13: Domain cost (per month, amortized) | C13: 1.25
B14: Tools/software (per month, flat across all clients) | C14: 20
B15: Payment processing fee | C15: 0.03
B17: Sales Funnel Assumptions
B18: Item | C18: Value
B19: Outreach contacts per week (calls/emails/walk-ins) | C19: 20
B20: Contact → conversation rate | C20: 0.25
B21: Conversation → client conversion rate | C21: 0.12
B22: % of new clients who also take the care plan | C22: 0.85
B23: Monthly care-plan client churn rate | C23: 0.04
B25: Goal
B26: Item | C26: Value
B27: Target monthly income | C27: 5000

Sheet Monthly Projection
A1: 12-Month Projection
B2: New clients/month below defaults to the funnel calculation from Assumptions — overwrite any month (yellow) to model a slower or faster start.
B3: Metric | C3: Month 1 | D3: Month 2 | E3: Month 3 | F3: Month 4 | G3: Month 5 | H3: Month 6 | I3: Month 7 | J3: Month 8 | K3: Month 9 | L3: Month 10 | M3: Month 11 | N3: Month 12
B4: New clients won this month | C4: =ROUND(Assumptions!C19*4*Assumptions!C20*Assumptions!C21,0) -> 2 | D4: =C4 -> 2 | E4: =D4 -> 2 | F4: =E4 -> 2 | G4: =F4 -> 2 | H4: =G4 -> 2 | I4: =H4 -> 2 | J4: =I4 -> 2 | K4: =J4 -> 2 | ... N4: =M4 -> 2
B5: Cumulative active care-plan clients | C5: =ROUND(C4*Assumptions!C22,0) -> 2 | D5: =ROUND(C5*(1-Assumptions!C23)+D4*Assumptions!C22,0) -> 4 | E5: =ROUND(D5*(1-Assumptions!C23)+E4*Assumptions!C22,0) -> 6 | F5: =ROUND(E5*(1-Assumptions!C23)+F4*Assumptions!C22,0) -> 7 | G5: =ROUND(F5*(1-Assumptions!C23)+G4*Assumptions!C22,0) -> 8 | H5: =ROUND(G5*(1-Assumptions!C23)+H4*Assumptions!C22,0) -> 9 | I5: =ROUND(H5*(1-Assumptions!C23)+I4*Assumptions!C22,0) -> 10 | J5: =ROUND(I5*(1-Assumptions!C23)+J4*Assumptions!C22,0) -> 11 | K5: =ROUND(J5*(1-Assumptions!C23)+K4*Assumptions!C22,0) -> 12 | L5: =ROUND(K5*(1-Assumptions!C23)+L4*Assumptions!C22,0) -> 13 | M5: =ROUND(L5*(1-Assumptions!C23)+M4*Assumptions!C22,0) -> 14 | N5: =ROUND(M5*(1-Assumptions!C23)+N4*Assumptions!C22,0) -> 15
B6: Build revenue (one-time fees) | C6: =C4*Assumptions!C5 -> 2400 | D6: =D4*Assumptions!C5 -> 2400 | E6: =E4*Assumptions!C5 -> 2400 | F6: =F4*Assumptions!C5 -> 2400 | G6: =G4*Assumptions!C5 -> 2400 | H6: =H4*Assumptions!C5 -> 2400 | I6: =I4*Assumptions!C5 -> 2400 | J6: =J4*Assumptions!C5 -> 2400 | K6: =K4*Assumptions!C5 -> 2400 | L6: =L4*Assumptions!C5 -> 2400 | M6: =M4*Assumptions!C5 -> 2400 | N6: =N4*Assumptions!C5 -> 2400
B7: Care plan revenue (recurring) | C7: =C5*Assumptions!C7 -> 198 | D7: =D5*Assumptions!C7 -> 396 | E7: =E5*Assumptions!C7 -> 594 | F7: =F5*Assumptions!C7 -> 693 | G7: =G5*Assumptions!C7 -> 792 | H7: =H5*Assumptions!C7 -> 891 | I7: =I5*Assumptions!C7 -> 990 | J7: =J5*Assumptions!C7 -> 1089 | K7: =K5*Assumptions!C7 -> 1188 | L7: =L5*Assumptions!C7 -> 1287 | M7: =M5*Assumptions!C7 -> 1386 | N7: =N5*Assumptions!C7 -> 1485
B8: Total revenue | C8: =C6+C7 -> 2598 | D8: =D6+D7 -> 2796 | E8: =E6+E7 -> 2994 | F8: =F6+F7 -> 3093 | G8: =G6+G7 -> 3192 | H8: =H6+H7 -> 3291 | I8: =I6+I7 -> 3390 | J8: =J6+J7 -> 3489 | ... N8: =N6+N7 -> 3885
B9: Hosting + domain costs | C9: =C5*(Assumptions!C12+Assumptions!C13) -> 8.5 | D9: =D5*(Assumptions!C12+Assumptions!C13) -> 17 | E9: =E5*(Assumptions!C12+Assumptions!C13) -> 25.5 | F9: =F5*(Assumptions!C12+Assumptions!C13) -> 29.75 | G9: =G5*(Assumptions!C12+Assumptions!C13) -> 34 | H9: =H5*(Assumptions!C12+Assumptions!C13) -> 38.25 | I9: =I5*(Assumptions!C12+Assumptions!C13) -> 42.5 | J9: =J5*(Assumptions!C12+Assumptions!C13) -> 46.75 | K9: =K5*(Assumptions!C12+Assumptions!C13) -> 51 | L9: =L5*(Assumptions!C12+Assumptions!C13) -> 55.25 | M9: =M5*(Assumptions!C12+Assumptions!C13) -> 59.5 | N9: =N5*(Assumptions!C12+Assumptions!C13) -> 63.75
B10: Payment processing fees | C10: =C8*Assumptions!C15 -> 77.94 | D10: =D8*Assumptions!C15 -> 83.88 | E10: =E8*Assumptions!C15 -> 89.82 | F10: =F8*Assumptions!C15 -> 92.79 | G10: =G8*Assumptions!C15 -> 95.76 | H10: =H8*Assumptions!C15 -> 98.73 | I10: =I8*Assumptions!C15 -> 101.7 | J10: =J8*Assumptions!C15 -> 104.67 | K10: =K8*Assumptions!C15 -> 107.64 | L10: =L8*Assumptions!C15 -> 110.61 | M10: =M8*Assumptions!C15 -> 113.58 | N10: =N8*Assumptions!C15 -> 116.55
B11: Tools/software (flat) | C11: =Assumptions!C14 -> 20 | D11: =Assumptions!C14 -> 20 | E11: =Assumptions!C14 -> 20 | F11: =Assumptions!C14 -> 20 | G11: =Assumptions!C14 -> 20 | H11: =Assumptions!C14 -> 20 | I11: =Assumptions!C14 -> 20 | J11: =Assumptions!C14 -> 20 | K11: =Assumptions!C14 -> 20 | L11: =Assumptions!C14 -> 20 | M11: =Assumptions!C14 -> 20 | N11: =Assumptions!C14 -> 20
B12: Total costs | C12: =C9+C10+C11 -> 106.44 | D12: =D9+D10+D11 -> 120.88 | E12: =E9+E10+E11 -> 135.32 | F12: =F9+F10+F11 -> 142.54 | G12: =G9+G10+G11 -> 149.76 | H12: =H9+H10+H11 -> 156.98 | I12: =I9+I10+I11 -> 164.2 | J12: =J9+J10+J11 -> 171.42 | ... N12: =N9+N10+N11 -> 200.3
B13: Monthly profit | C13: =C8-C12 -> 2491.56 | D13: =D8-D12 -> 2675.12 | E13: =E8-E12 -> 2858.68 | F13: =F8-F12 -> 2950.46 | G13: =G8-G12 -> 3042.24 | H13: =H8-H12 -> 3134.02 | I13: =I8-I12 -> 3225.8 | J13: =J8-J12 -> 3317.58 | ... N13: =N8-N12 -> 3684.7
B14: Gap to $5K goal | C14: =Assumptions!C27-C13 -> 2508.44 | D14: =Assumptions!C27-D13 -> 2324.88 | E14: =Assumptions!C27-E13 -> 2141.32 | F14: =Assumptions!C27-F13 -> 2049.54 | G14: =Assumptions!C27-G13 -> 1957.76 | H14: =Assumptions!C27-H13 -> 1865.98 | I14: =Assumptions!C27-I13 -> 1774.2 | J14: =Assumptions!C27-J13 -> 1682.42 | K14: =Assumptions!C27-K13 -> 1590.64 | L14: =Assumptions!C27-L13 -> 1498.86 | M14: =Assumptions!C27-M13 -> 1407.08 | N14: =Assumptions!C27-N13 -> 1315.3

Sheet Path to $5K
A1: Path to $5,000/Month — Scenario Comparison
B3: Scenario A — New Builds Only (no recurring revenue) | G3: Two ways to hit the same income goal. The 'New builds only' scenario requires selling every single month forever — miss a month, income drops to zero. The 'Recurring-heavy' scenario builds a stable income floor from care-plan clients, topped up with fewer new sales needed each month. This is why the plan recommends prioritizing the care plan attach rate.
B4: Metric | C4: Value
B5: Build fee per client | C5: =Assumptions!C5 -> 1200
B6: New clients needed per month for $5K | C6: =ROUNDUP(Assumptions!C27/C5,0) -> 5
B7: Sustaining this requires winning this many NEW clients every single month, indefinitely — a constant treadmill with no income floor.
B9: Scenario B — Recurring-Heavy (recommended)
B10: Metric | C10: Value
B11: Target recurring (care-plan) clients | C11: 25
B12: Care plan fee | C12: =Assumptions!C7 -> 99
B13: Recurring income floor | C13: =C11*C12 -> 2475
B14: Remaining gap to close with new builds | C14: =MAX(Assumptions!C27-C13,0) -> 2525
B15: New builds needed per month to close gap | C15: =ROUNDUP(C14/Assumptions!C5,0) -> 3
B16: Once you reach the target recurring client count, you only need this many new builds per month — far more forgiving than Scenario A, and income doesn't reset to zero in a slow month.
B18: How many months to build the recurring base?
B19: Metric | C19: Value
B20: New clients won per month (from Assumptions funnel) | C20: =ROUND(Assumptions!C19*4*Assumptions!C20*Assumptions!C21,1) -> 2.4
B21: % of new clients who take the care plan | C21: =Assumptions!C22 -> 0.85
B22: New recurring clients added per month | C22: =C20*C21 -> 2.04
B23: Months to reach target recurring client count* | C23: =ROUNDUP(C11/C22,0) -> 13
B24: *Simplified estimate ignoring churn — see Monthly Projection tab for the churn-adjusted month-by-month build-out.

Sheet Lead Tracker
A1: Lead Tracker
B2: Log prospects found via Google Maps/Yelp here. Status dropdown and conditional color-coding included. Add rows as needed — formatting will not auto-extend past row 60, copy the row format down if you need more.
B3: Business Name | C3: Niche/Category | D3: # Reviews | E3: Rating | F3: Phone / Contact | G3: Source (Maps/Yelp/Drive-by) | H3: Outreach Date | I3: Status | J3: Next Follow-up | K3: Notes

Sheet Search Query List
A1: Search Query List — North Dallas Blue-Collar Trades
B2: Run each row as a separate Google Maps search (e.g. "HVAC repair Frisco TX") — Google Maps caps results around 120 per area, so searching by suburb instead of the whole metro avoids missing listings. Paste the Search Query directly into Google Maps or your scraping tool. Track progress in the yellow columns as you go.
B3: Trade Category | C3: Suburb | D3: Search Query (paste into Google Maps) | E3: Date Run | F3: # Results | G3: # No-Website Leads | H3: Notes | I3: Status
B4: HVAC repair | C4: Frisco TX | D4: HVAC repair Frisco TX
B5: HVAC repair | C5: Plano TX | D5: HVAC repair Plano TX
B6: HVAC repair | C6: McKinney TX | D6: HVAC repair McKinney TX
B7: HVAC repair | C7: Allen TX | D7: HVAC repair Allen TX
B8: HVAC repair | C8: The Colony TX | D8: HVAC repair The Colony TX
B9: HVAC repair | C9: Prosper TX | D9: HVAC repair Prosper TX
B10: Plumbing | C10: Frisco TX | D10: Plumbing Frisco TX
B11: Plumbing | C11: Plano TX | D11: Plumbing Plano TX
B12: Plumbing | C12: McKinney TX | D12: Plumbing McKinney TX
B13: Plumbing | C13: Allen TX | D13: Plumbing Allen TX
B14: Plumbing | C14: The Colony TX | D14: Plumbing The Colony TX
B15: Plumbing | C15: Prosper TX | D15: Plumbing Prosper TX
... B75: Pool service repair | C75: Prosper TX | D75: Pool service repair Prosper TX
B78: Total searches: | C78: =COUNTA(D4:D75) -> 72
B79: Searches done: | C79: =COUNTIF(I4:I75,"Done") -> 0
B80: Total no-website leads found: | C80: =SUM(G4:G75) -> 0
B82: Tip: work top-to-bottom by trade, not suburb — staying in one trade category at a time keeps your sample homepage / pitch consistent across calls, per the niche-down strategy.
